{"type":"PR","pr":{"number":181,"head":"875ccad255d8eccd4d4c5dd946a0f6947de228ea"},"user":"info","status":"pending_publish","branch":"cms/seb-toots","collection":"portoflio-fr","title":"Seb Toots: livre commandite | Rédaction agile","description":"Un portfolio a été rédigé dans le but d’aller chercher de nouveaux commanditaires pour Seb Toots. Découvrir le projet.","objects":{"entry":{"path":"content/portfolio/seb-toots.md","sha":"6b52088382efc28ba9e6d2ba71c74102701a88fe"},"files":[{"path":"/themes/saralarin/source-images/sebtoots-low.jpg","sha":"191b7d3aacf4cab51f091f37948e9315cee63486"}]},"timeStamp":"2018-07-05T00:32:59.107Z"}